odoo8_addon_sale_product_multi_add-8.0.1.0.0-py2.7-nspkg.pth
odoo8_addon_sale_product_multi_add-8.0.1.0.0.dist-info/DESCRIPTION.rst
odoo8_addon_sale_product_multi_add-8.0.1.0.0.dist-info/METADATA
odoo8_addon_sale_product_multi_add-8.0.1.0.0.dist-info/RECORD
odoo8_addon_sale_product_multi_add-8.0.1.0.0.dist-info/WHEEL
odoo8_addon_sale_product_multi_add-8.0.1.0.0.dist-info/metadata.json
odoo8_addon_sale_product_multi_add-8.0.1.0.0.dist-info/namespace_packages.txt
odoo8_addon_sale_product_multi_add-8.0.1.0.0.dist-info/top_level.txt
odoo_addons/sale_product_multi_add/README.rst
odoo_addons/sale_product_multi_add/__init__.py
odoo_addons/sale_product_multi_add/__openerp__.py
odoo_addons/sale_product_multi_add/tests/__init__.py
odoo_addons/sale_product_multi_add/tests/test_sale.py
odoo_addons/sale_product_multi_add/views/sale_view.xml
odoo_addons/sale_product_multi_add/wizard/__init__.py
odoo_addons/sale_product_multi_add/wizard/sale_import_products.py
odoo_addons/sale_product_multi_add/wizard/sale_import_products_view.xml
